vies/__init__.py
vies/_version.py
vies/models.py
vies/types.py
vies/validators.py
vies/forms/__init__.py
vies/forms/fields.py
vies/forms/widgets.py
vies/locale/ES/LC_MESSAGES/django.mo
vies/locale/ES/LC_MESSAGES/django.po
vies/locale/da/LC_MESSAGES/django.mo
vies/locale/da/LC_MESSAGES/django.po
vies/locale/de/LC_MESSAGES/django.mo
vies/locale/de/LC_MESSAGES/django.po
vies/locale/fr/LC_MESSAGES/django.mo
vies/locale/fr/LC_MESSAGES/django.po
vies/locale/it/LC_MESSAGES/django.mo
vies/locale/it/LC_MESSAGES/django.po
vies/locale/nl/LC_MESSAGES/django.mo
vies/locale/nl/LC_MESSAGES/django.po
vies/locale/pl/LC_MESSAGES/django.mo
vies/locale/pl/LC_MESSAGES/django.po
django_vies-6.2.1.dist-info/licenses/LICENSE
django_vies-6.2.1.dist-info/WHEEL
django_vies-6.2.1.dist-info/METADATA
django_vies-6.2.1.dist-info/RECORD
