Metadata-Version: 2.4
Name: django-vies
Version: 6.2.1
Summary: Validate and store VAT Information Exchange System (VIES) data in Django.
Author-email: Johannes Hoppe <info@johanneshoppe.com>
Requires-Python: >=3.10
License-Expression: MIT
Classifier: Development Status :: 5 - Production/Stable
Classifier: Environment :: Web Environment
Classifier: Operating System :: OS Independent
Classifier: Intended Audience :: Developers
Classifier: Intended Audience :: Financial and Insurance Industry
Classifier: Programming Language :: Python :: 3
Classifier: Programming Language :: Python :: 3 :: Only
Classifier: Programming Language :: Python :: 3.10
Classifier: Programming Language :: Python :: 3.11
Classifier: Programming Language :: Python :: 3.12
Classifier: Programming Language :: Python :: 3.13
Classifier: Programming Language :: Python :: 3.14
Classifier: Framework :: Django
Classifier: Framework :: Django :: 4.2
Classifier: Framework :: Django :: 5.1
Classifier: Framework :: Django :: 5.2
Classifier: Topic :: Software Development
Classifier: Topic :: Office/Business :: Financial :: Accounting
License-File: LICENSE
Requires-Dist: Django>=4.2
Requires-Dist: retrying>=1.1.0
Requires-Dist: zeep>=2.5.0
Requires-Dist: ruff==0.14.0 ; extra == "lint"
Requires-Dist: msgcheck==4.1.0 ; extra == "lint"
Requires-Dist: pytest ; extra == "test"
Requires-Dist: pytest-cov ; extra == "test"
Requires-Dist: pytest-django ; extra == "test"
Provides-Extra: lint
Provides-Extra: test
